p360_contact_manager/__init__.py
p360_contact_manager/api/__init__.py
p360_contact_manager/api/brreg.py
p360_contact_manager/api/p360.py
p360_contact_manager/arguments.py
p360_contact_manager/cli.py
p360_contact_manager/common.py
p360_contact_manager/constants.py
p360_contact_manager/environment_variables.py
p360_contact_manager/injected.py
p360_contact_manager/settings.py
p360_contact_manager/usecases/__init__.py
p360_contact_manager/usecases/brreg_syncronize.py
p360_contact_manager/usecases/cache.py
p360_contact_manager/usecases/check_malformed.py
p360_contact_manager/usecases/duplicates.py
p360_contact_manager/usecases/enrich.py
p360_contact_manager/usecases/ping.py
p360_contact_manager/usecases/synchronize.py
p360_contact_manager/usecases/update.py
p360_contact_manager-1.2.0.dist-info/entry_points.txt
p360_contact_manager-1.2.0.dist-info/LICENSE
p360_contact_manager-1.2.0.dist-info/WHEEL
p360_contact_manager-1.2.0.dist-info/METADATA
p360_contact_manager-1.2.0.dist-info/RECORD
