Metadata-Version: 2.1
Name: p360-contact-manager
Version: 1.2.0
Summary: Public 360 application by Tieto has some issues with for example duplicated contacts. This package tries to fix that and adds other functionality like synchronization(enrichment) with brreg.no.
Home-page: https://pypi.org/project/p360-contact-manager
License: Apache-2.0
Keywords: Public 360,Contact Manager,Contact Duplication fix,BRREG.no Synchronize Enrichment,Functional Programming
Author: Thomas Borgen
Author-email: thomas.borgen@greenbird.com
Requires-Python: >=3.6,<4.0
Classifier: Development Status :: 4 - Beta
Classifier: Intended Audience :: Developers
Classifier: License :: OSI Approved :: Apache Software License
Classifier: Operating System :: OS Independent
Classifier: Programming Language :: Python :: 3
Classifier: Programming Language :: Python :: 3.6
Classifier: Programming Language :: Python :: 3.7
Classifier: Programming Language :: Python :: 3.8
Classifier: Topic :: Software Development :: Libraries :: Python Modules
Classifier: Topic :: Utilities
Requires-Dist: attrs (>=20.3.0,<21.0.0)
Requires-Dist: dependencies (>=2.0.0,<3.0.0)
Requires-Dist: iso3166 (>=1.0,<2.0)
Requires-Dist: requests (>=2.24.0,<3.0.0)
Requires-Dist: returns (>=0.14.0,<0.15.0)
Project-URL: Documentation, https://greenbird.github.io/p360-contact-manager
Project-URL: Repository, https://github.com/greenbird/p360-contact-manager
